<annotation>
	<folder>pedestrian crossing</folder>
	<filename>1960.jpg</filename>
	<path>C:\Users\LAVUDI SAIKIRAN\Desktop\New folder\pedestrian crossing\1960.jpg</path>
	<source>
		<database>Unknown</database>
	</source>
	<size>
		<width>2240</width>
		<height>4000</height>
		<depth>3</depth>
	</size>
	<segmented>0</segmented>
	<object>
		<name>pedestrain crossing</name>
		<pose>Unspecified</pose>
		<truncated>0</truncated>
		<difficult>0</difficult>
		<bndbox>
			<xmin>126</xmin>
			<ymin>606</ymin>
			<xmax>1739</xmax>
			<ymax>2269</ymax>
		</bndbox>
	</object>
</annotation>
