<annotation>
	<folder>turn left</folder>
	<filename>9966237.jpg</filename>
	<path>C:\turn left\9966237.jpg</path>
	<source>
		<database>Unknown</database>
	</source>
	<size>
		<width>2240</width>
		<height>4000</height>
		<depth>3</depth>
	</size>
	<segmented>0</segmented>
	<object>
		<name>Turn left</name>
		<pose>Unspecified</pose>
		<truncated>0</truncated>
		<difficult>0</difficult>
		<bndbox>
			<xmin>148</xmin>
			<ymin>722</ymin>
			<xmax>2210</xmax>
			<ymax>2609</ymax>
		</bndbox>
	</object>
</annotation>
